newrcc/__init__.py
newrcc/c_color.py
newrcc/c_console.py
newrcc/c_error.py
newrcc-0.5.1.dist-info/METADATA
newrcc-0.5.1.dist-info/WHEEL
newrcc-0.5.1.dist-info/top_level.txt
newrcc-0.5.1.dist-info/RECORD
