Metadata-Version: 2.4
Name: newrcc
Version: 0.5.1
Summary: A tool that can make your console output beautiful.
Author: RestRegular
Author-email: 3228097751@qq.com
Classifier: Programming Language :: Python :: 3
Classifier: License :: OSI Approved :: MIT License
Classifier: Operating System :: OS Independent
Dynamic: author
Dynamic: author-email
Dynamic: classifier
Dynamic: description
Dynamic: description-content-type
Dynamic: summary
